rscli/__init__.py
rscli/main.py
rscli/tasks.py
rscli/utils.py
rscli/version.py
rscli-2019.1a5.dist-info/LICENSE
rscli-2019.1a5.dist-info/METADATA
rscli-2019.1a5.dist-info/WHEEL
rscli-2019.1a5.dist-info/entry_points.txt
rscli-2019.1a5.dist-info/top_level.txt
rscli-2019.1a5.dist-info/RECORD
